rectangle/__init__.py
rectangle/py.typed
rectangle/rectangle.py
rectangle-0.5.1.dist-info/METADATA
rectangle-0.5.1.dist-info/WHEEL
rectangle-0.5.1.dist-info/licenses/LICENSE
rectangle-0.5.1.dist-info/RECORD
