Metadata-Version: 2.4
Name: rectangle
Version: 0.5.1
Summary: A class for handling rectangle regions.
Project-URL: repository, https://github.com/NeilGirdhar/rectangle
Author: Neil Girdhar
Author-email: mistersheik@gmail.com
Maintainer: Neil Girdhar
Maintainer-email: mistersheik@gmail.com
License: MIT License
License-File: LICENSE
Classifier: Development Status :: 5 - Production/Stable
Classifier: Intended Audience :: Developers
Classifier: License :: OSI Approved :: Apache Software License
Classifier: License :: OSI Approved :: MIT License
Classifier: Operating System :: OS Independent
Classifier: Programming Language :: Python
Classifier: Programming Language :: Python :: 3
Classifier: Programming Language :: Python :: 3.10
Classifier: Programming Language :: Python :: 3.11
Classifier: Programming Language :: Python :: 3.12
Classifier: Topic :: Software Development :: Libraries :: Python Modules
Requires-Python: <3.13,>=3.10
Requires-Dist: numpy>=1.21
